readme_page.py
readme_page-1.0.0.data/scripts/readme-page
readme_page-1.0.0.dist-info/METADATA
readme_page-1.0.0.dist-info/metadata.json
readme_page-1.0.0.dist-info/DESCRIPTION.rst
readme_page-1.0.0.dist-info/WHEEL
readme_page-1.0.0.dist-info/top_level.txt
readme_page-1.0.0.dist-info/RECORD
