Metadata-Version: 2.0
Name: readme-page
Version: 1.0.0
Summary: A script to create a readme GitHub Page for your project.
Home-page: https://github.com/fernandojunior/readme-page
Author: Fernando Felix do Nascimento Junior
Author-email: fernandojr.ifcg@live.com
License: MIT License
Platform: UNKNOWN
Classifier: Development Status :: 5 - Production/Stable
Classifier: License :: OSI Approved :: MIT License
Classifier: Natural Language :: English
Classifier: Operating System :: OS Independent
Classifier: Programming Language :: Python :: 2
Classifier: Programming Language :: Python :: 2.6
Classifier: Programming Language :: Python :: 2.7
Classifier: Programming Language :: Python :: 3
Classifier: Programming Language :: Python :: 3.3
Classifier: Programming Language :: Python :: 3.4
Classifier: Programming Language :: Python :: 3.5
Requires-Dist: mkdocs (==0.15.3)
Requires-Dist: mkdocs-bootstrap (==0.1.1)
Requires-Dist: six (==1.10.0)
Requires-Dist: beautifulsoup4 (==4.1.1)
